guerrillamail.py
python_guerrilla_mail_brb-0.1.1.dist-info/LICENSE
python_guerrilla_mail_brb-0.1.1.dist-info/METADATA
python_guerrilla_mail_brb-0.1.1.dist-info/WHEEL
python_guerrilla_mail_brb-0.1.1.dist-info/entry_points.txt
python_guerrilla_mail_brb-0.1.1.dist-info/top_level.txt
python_guerrilla_mail_brb-0.1.1.dist-info/RECORD
