Metadata-Version: 2.1
Name: python-guerrilla-mail-brb
Version: 0.1.1
Summary: Client for the Guerrillamail temporary email server
Home-page: https://github.com/sutkyne/python-guerrillamail
Author: Nathan Jones
License: GPL3
Keywords: guerrillamail email client cli
Classifier: Development Status :: 5 - Production/Stable
Classifier: Intended Audience :: Developers
Classifier: Natural Language :: English
Classifier: License :: OSI Approved :: GNU General Public License v3 or later (GPLv3+)
Classifier: Programming Language :: Python
Classifier: Programming Language :: Python :: 2
Classifier: Programming Language :: Python :: 2.7
Classifier: Programming Language :: Python :: 3
Classifier: Programming Language :: Python :: 3.3
Classifier: Programming Language :: Python :: 3.4
Classifier: Programming Language :: Python :: 3.5
Classifier: Programming Language :: Python :: 3.11
License-File: LICENSE
Requires-Dist: requests
